thalamus/__init__.py
thalamus/thalamus.py
thalamus/demo/federation_schema.sql
thalamus/demo/import_pg.py
thalamus/demo/newborn.jpg
thalamus/demo/people.json
thalamus/demo/personal_docs.json
thalamus/demo/pols.json
thalamus/demo/populate.sh
thalamus/doc/thalamus.rst
thalamus/etc/gunicorn.cfg
thalamus/etc/roles.cfg
thalamus/etc/thalamus.cfg
thalamus/etc/thalamus_uwsgi.ini
thalamus/static/style.css
thalamus/templates/index.html
thalamus/templates/password.html
thalamus-0.9.16.dist-info/LICENSE
thalamus-0.9.16.dist-info/METADATA
thalamus-0.9.16.dist-info/WHEEL
thalamus-0.9.16.dist-info/top_level.txt
thalamus-0.9.16.dist-info/RECORD
