Metadata-Version: 2.1
Name: thalamus
Version: 0.9.16
Summary: The GNU Health Federation Message and Authentication Server
Home-page: https://www.gnuhealth.org
Download-URL: http://ftp.gnu.org/gnu/health
Author: GNU Solidario
Author-email: health@gnusolidario.org
Keywords: health API REST
Platform: any
Classifier: Development Status :: 4 - Beta
Classifier: Environment :: Web Environment
Classifier: Framework :: Flask
Classifier: Intended Audience :: Science/Research
Classifier: Intended Audience :: Healthcare Industry
Classifier: License :: OSI Approved :: GNU General Public License v3 or later (GPLv3+)
Classifier: Natural Language :: English
Classifier: Operating System :: OS Independent
Classifier: Programming Language :: Python :: 3
Classifier: Topic :: Scientific/Engineering :: Bio-Informatics
Classifier: Topic :: Scientific/Engineering :: Medical Science Apps.
License-File: LICENSE
Requires-Dist: flask
Requires-Dist: flask-cors
Requires-Dist: flask-httpauth
Requires-Dist: flask-restful
Requires-Dist: flask-wtf
Requires-Dist: psycopg2
Requires-Dist: bcrypt
